patent_chart/__init__.py
patent_chart/citation.py
patent_chart/data_structures.py
patent_chart/embeddings.py
patent_chart/evaluation.py
patent_chart/filtering.py
patent_chart/generator.py
patent_chart/google_patents.py
patent_chart/integrationtests.py
patent_chart/parser.py
patent_chart/pinecone.py
patent_chart/ranking.py
patent_chart/redis_utils.py
patent_chart/requests_utils.py
patent_chart/search_index.py
patent_chart/settings.py
patent_chart/tests.py
patent_chart/uspto_parse.py
patent_chart/utils.py
patent_chart-0.2.12.dist-info/METADATA
patent_chart-0.2.12.dist-info/WHEEL
patent_chart-0.2.12.dist-info/RECORD
