Metadata-Version: 2.1
Name: patent-chart
Version: 0.2.12
Summary: Automated invalidity contention charts
License: Proprietary
Author: Josh Hedtke
Requires-Python: >=3.11,<4.0
Classifier: License :: Other/Proprietary License
Classifier: Programming Language :: Python :: 3
Classifier: Programming Language :: Python :: 3.11
Classifier: Programming Language :: Python :: 3.12
Requires-Dist: anthropic (>=0.21.0,<0.22.0)
Requires-Dist: beautifulsoup4 (>=4.12.2,<5.0.0)
Requires-Dist: elasticsearch (>=8.12.1,<9.0.0)
Requires-Dist: huggingface-hub (>=0.21.3,<0.22.0)
Requires-Dist: langchain (>=0.1.14,<0.2.0)
Requires-Dist: openai (>=1.13.1,<2.0.0)
Requires-Dist: pandas (==2.1)
Requires-Dist: pdfminer-six (>=20221105,<20221106)
Requires-Dist: pinecone-client[grpc] (>=3.2.1,<4.0.0)
Requires-Dist: pydantic (>=2.4.2,<3.0.0)
Requires-Dist: python-dotenv (>=1.0.0,<2.0.0)
Requires-Dist: redis (>=5.0.1,<6.0.0)
Requires-Dist: requests-aws4auth (>=1.2.3,<2.0.0)
Requires-Dist: tenacity (>=8.2.3,<9.0.0)
Requires-Dist: tiktoken (>=0.5.1,<0.6.0)
